soarca_fin_python_library/__init__.py
soarca_fin_python_library/abstract_classes/i_executor.py
soarca_fin_python_library/abstract_classes/i_mqtt_client.py
soarca_fin_python_library/abstract_classes/i_parser.py
soarca_fin_python_library/abstract_classes/i_soarca_fin.py
soarca_fin_python_library/enums/__init__.py
soarca_fin_python_library/enums/ack_status_enum.py
soarca_fin_python_library/enums/auth_type_enum.py
soarca_fin_python_library/enums/dispatcher_task_enum.py
soarca_fin_python_library/enums/timeout_status_enum.py
soarca_fin_python_library/enums/variable_type_enum.py
soarca_fin_python_library/enums/workflow_step_enum.py
soarca_fin_python_library/executor.py
soarca_fin_python_library/models/__init__.py
soarca_fin_python_library/models/ack.py
soarca_fin_python_library/models/agent_structure.py
soarca_fin_python_library/models/authentication_information.py
soarca_fin_python_library/models/capability_structure.py
soarca_fin_python_library/models/command.py
soarca_fin_python_library/models/command_sub_structure.py
soarca_fin_python_library/models/context.py
soarca_fin_python_library/models/external_reference.py
soarca_fin_python_library/models/message.py
soarca_fin_python_library/models/meta.py
soarca_fin_python_library/models/nack.py
soarca_fin_python_library/models/register.py
soarca_fin_python_library/models/result.py
soarca_fin_python_library/models/result_structure.py
soarca_fin_python_library/models/security.py
soarca_fin_python_library/models/step_structure.py
soarca_fin_python_library/models/unregister.py
soarca_fin_python_library/models/unregister_self.py
soarca_fin_python_library/models/variable.py
soarca_fin_python_library/mqtt_client.py
soarca_fin_python_library/parser.py
soarca_fin_python_library/soarca_fin.py
soarca_fin_library-1.0.0.dist-info/LICENSE
soarca_fin_library-1.0.0.dist-info/METADATA
soarca_fin_library-1.0.0.dist-info/WHEEL
soarca_fin_library-1.0.0.dist-info/RECORD
