Metadata-Version: 2.1
Name: soarca-fin-library
Version: 1.0.0
Summary: SOARCA FIN lib allows for extending custom SOARCA capabilities through a python library
License: Apache-2.0
Author: Maarten de Kruijf
Requires-Python: >=3.10,<4.0
Classifier: License :: OSI Approved :: Apache Software License
Classifier: Programming Language :: Python :: 3
Classifier: Programming Language :: Python :: 3.10
Classifier: Programming Language :: Python :: 3.11
Classifier: Programming Language :: Python :: 3.12
Requires-Dist: paho-mqtt (==2.0.0)
Requires-Dist: pydantic (==2.6.4)
Requires-Dist: python-dotenv (==1.0.1)
